NCrystal/__init__.py
NCrystal/__main__.py
NCrystal/_chooks.py
NCrystal/_cli_cif2ncmat.py
NCrystal/_cli_endf2ncmat.py
NCrystal/_cli_hfg2ncmat.py
NCrystal/_cli_mcstasunion.py
NCrystal/_cli_ncmat2cpp.py
NCrystal/_cli_ncmat2endf.py
NCrystal/_cli_ncmat2hkl.py
NCrystal/_cli_nctool.py
NCrystal/_cli_vdos2ncmat.py
NCrystal/_cli_verifyatompos.py
NCrystal/_cliimpl.py
NCrystal/_cliwrap_config.py
NCrystal/_common.py
NCrystal/_coreimpl.py
NCrystal/_hfgdata.py
NCrystal/_hist.py
NCrystal/_hklobjects.py
NCrystal/_is_std.py
NCrystal/_locatelib.py
NCrystal/_miscimpl.py
NCrystal/_mmc.py
NCrystal/_msg.py
NCrystal/_ncmat2cpp_impl.py
NCrystal/_ncmat2endf_impl.py
NCrystal/_ncmatimpl.py
NCrystal/_numpy.py
NCrystal/_sabutils.py
NCrystal/_testimpl.py
NCrystal/api.py
NCrystal/atomdata.py
NCrystal/cfgstr.py
NCrystal/cifutils.py
NCrystal/cli.py
NCrystal/constants.py
NCrystal/core.py
NCrystal/datasrc.py
NCrystal/exceptions.py
NCrystal/hfg2ncmat.py
NCrystal/mcstasutils.py
NCrystal/misc.py
NCrystal/mmc.py
NCrystal/ncmat.py
NCrystal/ncmat2cpp.py
NCrystal/ncmat2endf.py
NCrystal/obsolete.py
NCrystal/plot.py
NCrystal/plugins.py
NCrystal/test.py
NCrystal/vdos.py
ncrystal_python-4.2.12.dist-info/licenses/LICENSE
ncrystal_python-4.2.12.dist-info/METADATA
ncrystal_python-4.2.12.dist-info/WHEEL
ncrystal_python-4.2.12.dist-info/entry_points.txt
ncrystal_python-4.2.12.dist-info/top_level.txt
ncrystal_python-4.2.12.dist-info/RECORD
