Metadata-Version: 2.4
Name: ncrystal-python
Version: 4.2.12
Summary: Library for thermal neutron transport in crystals and other materials.
Author: NCrystal developers (Thomas Kittelmann, Xiao Xiao Cai)
License: 
Project-URL: Homepage, https://mctools.github.io/ncrystal/
Project-URL: Bug Tracker, https://github.com/mctools/ncrystal/issues
Classifier: Programming Language :: Python :: 3
Classifier: License :: OSI Approved :: Apache Software License
Requires-Python: >=3.8
License-File: LICENSE
Requires-Dist: numpy>=1.22
Dynamic: license-file
